odoo8_addon_donation_thanks-8.0.0.1.0-py2.7-nspkg.pth
odoo_addons/donation_thanks/__openerp__.py
odoo_addons/donation_thanks/donation_view.xml
odoo_addons/donation_thanks/report_thanks.xml
odoo_addons/donation_thanks/thanks.odt
odoo_addons/donation_thanks/__init__.py
odoo_addons/donation_thanks/README.rst
odoo_addons/donation_thanks/donation.py
odoo_addons/donation_thanks/i18n/donation_thanks.pot
odoo_addons/donation_thanks/i18n/fr.po
odoo_addons/donation_thanks/static/description/icon.png
odoo8_addon_donation_thanks-8.0.0.1.0.dist-info/top_level.txt
odoo8_addon_donation_thanks-8.0.0.1.0.dist-info/WHEEL
odoo8_addon_donation_thanks-8.0.0.1.0.dist-info/RECORD
odoo8_addon_donation_thanks-8.0.0.1.0.dist-info/metadata.json
odoo8_addon_donation_thanks-8.0.0.1.0.dist-info/DESCRIPTION.rst
odoo8_addon_donation_thanks-8.0.0.1.0.dist-info/METADATA
odoo8_addon_donation_thanks-8.0.0.1.0.dist-info/namespace_packages.txt
